qviz/__init__.py
qviz/_frontend.py
qviz/_version.py
qviz/model.py
qviz/source.py
qviz/transfer.py
qviz/adp/__init__.py
qviz/adp/base.py
qviz/adp/spark.py
qviz/labextension/qviz-0.1.0.tgz
qviz/loaders/__init__.py
qviz/loaders/base.py
qviz/loaders/cassandra_loader.py
qviz/nbextension/__init__.py
qviz/nbextension/static/extension.js
qviz/nbextension/static/index.js
qviz/nbextension/static/index.js.map
qviz/sources/__init__.py
qviz/sources/qbeast_v1.py
qviz/tests/__init__.py
qviz/tests/conftest.py
qviz/tests/test_nbextension_path.py
qviz/tests/test_qbeast_v1_source.py
qviz/tests/test_query_space.py
qviz/tests/test_qviz_qbeast_v1.py
qviz/ui/__init__.py
qviz/ui/base.py
qviz/ui/data_ingestion.py
qviz/ui/data_preparation.py
qviz-0.1.0.data/data/etc/jupyter/nbconfig/notebook.d/qviz.json
qviz-0.1.0.data/data/share/jupyter/lab/extensions/qviz-0.1.0.tgz
qviz-0.1.0.data/data/share/jupyter/nbextensions/qviz/extension.js
qviz-0.1.0.data/data/share/jupyter/nbextensions/qviz/index.js
qviz-0.1.0.data/data/share/jupyter/nbextensions/qviz/index.js.map
qviz-0.1.0.dist-info/LICENSE.txt
qviz-0.1.0.dist-info/METADATA
qviz-0.1.0.dist-info/WHEEL
qviz-0.1.0.dist-info/top_level.txt
qviz-0.1.0.dist-info/RECORD
